Mensajes/__init__.py
Mensajes/Hola/Saludos.py
Mensajes/Hola/__init__.py
Tests/__init__.py
Tests/test_hola.py
mensajes_NCM03-8.0.dist-info/LICENSE
mensajes_NCM03-8.0.dist-info/METADATA
mensajes_NCM03-8.0.dist-info/WHEEL
mensajes_NCM03-8.0.dist-info/top_level.txt
mensajes_NCM03-8.0.dist-info/RECORD
