Metadata-Version: 2.1
Name: mensajes-NCM03
Version: 8.0
Summary: un paquete para saludar y despedir
Home-page: https://www.noelia.dev
Author: Noelia
Author-email: Hola@Noelia.dev
Classifier: Environment :: Console
Classifier: Intended Audience :: Developers
Classifier: License :: OSI Approved :: MIT License
Classifier: Operating System :: OS Independent
Classifier: Programming Language :: Python
Classifier: Programming Language :: Python :: 3.11
Classifier: Topic :: Utilities
License-File: LICENSE
Requires-Dist: numpy >=1.25.2
